pseudo_bridgeland_tilt-0.2.0.dist-info/METADATA
pseudo_bridgeland_tilt-0.2.0.dist-info/WHEEL
pseudo_tilt/__init__.py
pseudo_tilt/pseudo_tilt.cpython-38-x86_64-linux-gnu.so
pseudo_bridgeland_tilt-0.2.0.dist-info/RECORD
